setup.py
wintoastlistener/__init__.py
wintoastlistener/exception.py
wintoastlistener/fetch_toast_payload.py
wintoastlistener/subscriber.py
wintoastlistener/utils.py
wintoastlistener-1.0.0.dist-info/LICENSE
wintoastlistener-1.0.0.dist-info/METADATA
wintoastlistener-1.0.0.dist-info/WHEEL
wintoastlistener-1.0.0.dist-info/top_level.txt
wintoastlistener-1.0.0.dist-info/RECORD
